hkmeans/hkmeans_optimizer_p.py
hkmeans/hkmeans_main.py
hkmeans/__init__.py
hkmeans/hkmeans_optimizer_c.py
hkmeans/_version.py
hkmeans/c_package/c_hkmeans_optimizer.pyx
hkmeans/c_package/__init__.py
hkmeans/c_package/hkmeans_optimizer.h
hkmeans/c_package/hkmeans_optimizer.cpp
hkmeans/c_package/c_hkmeans_optimizer.cpython-37m-x86_64-linux-gnu.so
hkmeans/c_package/c_hkmeans_optimizer.cpp
hkmeans/c_package/c_hkmeans_optimizer.pxd
hartigan_kmeans-0.0.6.dist-info/METADATA
hartigan_kmeans-0.0.6.dist-info/WHEEL
hartigan_kmeans-0.0.6.dist-info/RECORD
hartigan_kmeans-0.0.6.dist-info/LICENSE
hartigan_kmeans-0.0.6.dist-info/top_level.txt
